{
    "ShowGrade": false,
    "Year": {
        "2022": {
            "1": [
                {
                    "No": "1",
                    "Sec": "547",
                    "SubjIndex": "180",
                    "Code": "CC101",
                    "Description": "Introduction to Computer",
                    "Units": "3",
                    "Cat": "LEC",
                    "Lecdays": "M",
                    "From": "7:30 AM",
                    "To": "10:30 AM",
                    "Room": "CB1-207",
                    "Faculty": "Hidden",
                    "Pre": "",
                    "Mid": "",
                    "Fin": "",
                    "SemGrade": "",
                    "GradePts": "",
                    "Remarks": ""
                },
                {
                    "No": "2",
                    "Sec": "548",
                    "SubjIndex": "181",
                    "Code": "CC102",
                    "Description": "Computer Programming 1",
                    "Units": "3",
                    "Cat": "LEC",
                    "Lecdays": "M",
                    "From": "5:00 PM",
                    "To": "8:00 PM",
                    "Room": "Rm.110",
                    "Faculty": "Hidden",
                    "Pre": "",
                    "Mid": "",
                    "Fin": "",
                    "SemGrade": "",
                    "GradePts": "",
                    "Remarks": ""
                },
                {
                    "No": "3",
                    "Sec": "553",
                    "SubjIndex": "2",
                    "Code": "FIL101",
                    "Description": "Kontekstwalisadong Komunikasyon sa Filipino",
                    "Units": "3",
                    "Cat": "LEC",
                    "Lecdays": "T",
                    "From": "5:00 PM",
                    "To": "8:00 PM",
                    "Room": "Rm.110",
                    "Faculty": "Hidden",
                    "Pre": "",
                    "Mid": "",
                    "Fin": "",
                    "SemGrade": "",
                    "GradePts": "",
                    "Remarks": ""
                },
                {
                    "No": "4",
                    "Sec": "389",
                    "SubjIndex": "3",
                    "Code": "GEC1101",
                    "Description": "Understanding the Self",
                    "Units": "3",
                    "Cat": "LEC",
                    "Lecdays": "T",
                    "From": "2:00 PM",
                    "To": "5:00 PM",
                    "Room": "CB1-207",
                    "Faculty": "Hidden",
                    "Pre": "",
                    "Mid": "",
                    "Fin": "",
                    "SemGrade": "",
                    "GradePts": "",
                    "Remarks": ""
                },
                {
                    "No": "5",
                    "Sec": "555",
                    "SubjIndex": "4",
                    "Code": "GEC1102",
                    "Description": "Readings in Philippine History",
                    "Units": "3",
                    "Cat": "LEC",
                    "Lecdays": "S",
                    "From": "5:00 PM",
                    "To": "8:00 PM",
                    "Room": "Rm. No.205",
                    "Faculty": "Hidden",
                    "Pre": "",
                    "Mid": "",
                    "Fin": "",
                    "SemGrade": "",
                    "GradePts": "",
                    "Remarks": ""
                },
                {
                    "No": "6",
                    "Sec": "556",
                    "SubjIndex": "5",
                    "Code": "GEC1103",
                    "Description": "The Contemporary World",
                    "Units": "3",
                    "Cat": "LEC",
                    "Lecdays": "F",
                    "From": "7:30 AM",
                    "To": "10:30 AM",
                    "Room": "CB1-106",
                    "Faculty": "Hidden",
                    "Pre": "",
                    "Mid": "",
                    "Fin": "",
                    "SemGrade": "",
                    "GradePts": "",
                    "Remarks": ""
                },
                {
                    "No": "7",
                    "Sec": "550",
                    "SubjIndex": "6",
                    "Code": "GEC1104",
                    "Description": "Mathematics in the Modern World",
                    "Units": "3",
                    "Cat": "LEC",
                    "Lecdays": "H",
                    "From": "5:00 PM",
                    "To": "8:00 PM",
                    "Room": "CB1-102",
                    "Faculty": "Hidden",
                    "Pre": "",
                    "Mid": "",
                    "Fin": "",
                    "SemGrade": "",
                    "GradePts": "",
                    "Remarks": ""
                },
                {
                    "No": "8",
                    "Sec": "1019",
                    "SubjIndex": "182",
                    "Code": "HCI101",
                    "Description": "Introduction to Human Computer Interaction",
                    "Units": "3",
                    "Cat": "LEC",
                    "Lecdays": "H",
                    "From": "10:30 AM",
                    "To": "1:30 PM",
                    "Room": "CB1-109",
                    "Faculty": "Hidden",
                    "Pre": "",
                    "Mid": "",
                    "Fin": "",
                    "SemGrade": "",
                    "GradePts": "",
                    "Remarks": ""
                },
                {
                    "No": "9",
                    "Sec": "554",
                    "SubjIndex": "61",
                    "Code": "NSTP1",
                    "Description": "National Service Training Program 1 - ROTC 1",
                    "Units": "3",
                    "Cat": "LEC",
                    "Lecdays": "L",
                    "From": "8:00 AM",
                    "To": "12:00 PM",
                    "Room": "Rm.110",
                    "Faculty": "Hidden",
                    "Pre": "",
                    "Mid": "",
                    "Fin": "",
                    "SemGrade": "",
                    "GradePts": "",
                    "Remarks": ""
                },
                {
                    "No": "10",
                    "Sec": "549",
                    "SubjIndex": "9",
                    "Code": "PE-TA",
                    "Description": "Self-Testing Activity",
                    "Units": "2",
                    "Cat": "LEC",
                    "Lecdays": "S",
                    "From": "11:30 AM",
                    "To": "1:30 PM",
                    "Room": "CB2-308",
                    "Faculty": "Hidden",
                    "Pre": "",
                    "Mid": "",
                    "Fin": "",
                    "SemGrade": "",
                    "GradePts": "",
                    "Remarks": ""
                }
            ],
            "2": [
                {
                    "No": "1",
                    "Sec": "878",
                    "SubjIndex": "520",
                    "Code": "CC103",
                    "Description": "Computer Programming 2",
                    "Units": "3",
                    "Cat": "LEC",
                    "Lecdays": "S",
                    "From": "2:00 PM",
                    "To": "5:00 PM",
                    "Room": "CB2-310",
                    "Faculty": "Hidden",
                    "Pre": "",
                    "Mid": "",
                    "Fin": "",
                    "SemGrade": "",
                    "GradePts": "",
                    "Remarks": ""
                },
                {
                    "No": "2",
                    "Sec": "883",
                    "SubjIndex": "287",
                    "Code": "FIL 1202",
                    "Description": "Filipino sa Iba't - Ibang Disiplina",
                    "Units": "3",
                    "Cat": "LEC",
                    "Lecdays": "H",
                    "From": "5:30 PM",
                    "To": "8:30 PM",
                    "Room": "FCB-303",
                    "Faculty": "Hidden",
                    "Pre": "",
                    "Mid": "",
                    "Fin": "",
                    "SemGrade": "",
                    "GradePts": "",
                    "Remarks": ""
                },
                {
                    "No": "3",
                    "Sec": "879",
                    "SubjIndex": "288",
                    "Code": "GEC1205",
                    "Description": "Purposive Communication",
                    "Units": "3",
                    "Cat": "LEC",
                    "Lecdays": "M",
                    "From": "2:00 PM",
                    "To": "5:00 PM",
                    "Room": "CB2-308",
                    "Faculty": "Hidden",
                    "Pre": "",
                    "Mid": "",
                    "Fin": "",
                    "SemGrade": "",
                    "GradePts": "",
                    "Remarks": ""
                },
                {
                    "No": "4",
                    "Sec": "886",
                    "SubjIndex": "289",
                    "Code": "GEC1206",
                    "Description": "Art Appreciation",
                    "Units": "3",
                    "Cat": "LEC",
                    "Lecdays": "S",
                    "From": "7:30 AM",
                    "To": "10:30 AM",
                    "Room": "CB2-105",
                    "Faculty": "Hidden",
                    "Pre": "",
                    "Mid": "",
                    "Fin": "",
                    "SemGrade": "",
                    "GradePts": "",
                    "Remarks": ""
                },
                {
                    "No": "5",
                    "Sec": "880",
                    "SubjIndex": "160",
                    "Code": "GEC1207",
                    "Description": "Science, Technology and Society",
                    "Units": "3",
                    "Cat": "LEC",
                    "Lecdays": "M",
                    "From": "7:30 AM",
                    "To": "10:30 AM",
                    "Room": "CB2-302",
                    "Faculty": "Hidden",
                    "Pre": "",
                    "Mid": "",
                    "Fin": "",
                    "SemGrade": "",
                    "GradePts": "",
                    "Remarks": ""
                },
                {
                    "No": "6",
                    "Sec": "887",
                    "SubjIndex": "522",
                    "Code": "MS101",
                    "Description": "Discrete Mathematics",
                    "Units": "3",
                    "Cat": "LEC",
                    "Lecdays": "H",
                    "From": "10:30 AM",
                    "To": "1:30 PM",
                    "Room": "CB2-204",
                    "Faculty": "Hidden",
                    "Pre": "",
                    "Mid": "",
                    "Fin": "",
                    "SemGrade": "",
                    "GradePts": "",
                    "Remarks": ""
                },
                {
                    "No": "7",
                    "Sec": "884",
                    "SubjIndex": "587",
                    "Code": "MTH202",
                    "Description": "Trigonometry",
                    "Units": "3",
                    "Cat": "LEC",
                    "Lecdays": "H",
                    "From": "2:00 PM",
                    "To": "5:00 PM",
                    "Room": "CB2-204",
                    "Faculty": "Hidden",
                    "Pre": "",
                    "Mid": "",
                    "Fin": "",
                    "SemGrade": "",
                    "GradePts": "",
                    "Remarks": ""
                },
                {
                    "No": "8",
                    "Sec": "885",
                    "SubjIndex": "300",
                    "Code": "NSTP2",
                    "Description": "National Service Training Program 2 - ROTC 2",
                    "Units": "3",
                    "Cat": "LEC",
                    "Lecdays": "L",
                    "From": "8:00 AM",
                    "To": "12:00 PM",
                    "Room": "CB1-204",
                    "Faculty": "Hidden",
                    "Pre": "",
                    "Mid": "",
                    "Fin": "",
                    "SemGrade": "",
                    "GradePts": "",
                    "Remarks": ""
                },
                {
                    "No": "9",
                    "Sec": "882",
                    "SubjIndex": "721",
                    "Code": "PE 102",
                    "Description": "(PATH Fit 2) Exercise-based Fitness Activity",
                    "Units": "2",
                    "Cat": "LEC",
                    "Lecdays": "T",
                    "From": "6:00 PM",
                    "To": "8:00 PM",
                    "Room": "GYM 1 (CLOSED GYM)",
                    "Faculty": "Hidden",
                    "Pre": "",
                    "Mid": "",
                    "Fin": "",
                    "SemGrade": "",
                    "GradePts": "",
                    "Remarks": ""
                },
                {
                    "No": "10",
                    "Sec": "881",
                    "SubjIndex": "521",
                    "Code": "PT101",
                    "Description": "Platform Technologies",
                    "Units": "3",
                    "Cat": "LEC",
                    "Lecdays": "M",
                    "From": "5:00 PM",
                    "To": "8:00 PM",
                    "Room": "CB2-302",
                    "Faculty": "Hidden",
                    "Pre": "",
                    "Mid": "",
                    "Fin": "",
                    "SemGrade": "",
                    "GradePts": "",
                    "Remarks": ""
                }
            ]
        }
    }
}